anarchy_bot/__init__.py
anarchy_bot/__main__.py
anarchy_bot/bot.py
anarchy_bot/cb.py
anarchy_bot/chats.py
anarchy_bot/common.py
anarchy_bot/config.py
anarchy_bot/inline.py
anarchy_bot/lang.py
anarchy_bot/lists.py
anarchy_bot/main.py
anarchy_bot/msg.py
anarchy_bot/lang/en.yml
anarchy_bot-24.2.4.dist-info/METADATA
anarchy_bot-24.2.4.dist-info/WHEEL
anarchy_bot-24.2.4.dist-info/RECORD
