Metadata-Version: 2.1
Name: anarchy_bot
Version: 24.2.4
Summary: true anarchy in telegram chats
Project-URL: Documentation, https://t.me/gmanka
Project-URL: Bug Tracker, https://t.me/gmanka
Project-URL: Homepage, https://t.me/gmanka
Author-email: gmanka <gmankab@gmail.com>
Classifier: Operating System :: OS Independent
Classifier: Programming Language :: Python :: 3
Requires-Python: >=3.10
Requires-Dist: gmanka-yml
Requires-Dist: pyrogram
Requires-Dist: rich
Requires-Dist: tgcrypto
Requires-Dist: uvloop
